src/__init__.py
src/main.py
src/skewness dan kurtosis.py
src/tes.py
test/__init__.py
test/sample_test.py
Data_Statistik-0.1.dist-info/METADATA
Data_Statistik-0.1.dist-info/WHEEL
Data_Statistik-0.1.dist-info/top_level.txt
Data_Statistik-0.1.dist-info/RECORD
