Metadata-Version: 2.1
Name: Data_Statistik
Version: 0.1
Summary: Package ini bertujuan untuk membantu dalam mengolah data/nilai
Author: kelompok 2 B
Requires-Dist: pandas
